awsip/__init__.py
awsip/__main__.py
main/__init__.py
main/main.py
awsip-0.2.1.dist-info/LICENSE
awsip-0.2.1.dist-info/METADATA
awsip-0.2.1.dist-info/WHEEL
awsip-0.2.1.dist-info/entry_points.txt
awsip-0.2.1.dist-info/top_level.txt
awsip-0.2.1.dist-info/RECORD
