Metadata-Version: 2.1
Name: awsip
Version: 0.2.1
Summary: A simple package to check if ip address / range belongs to AWS.
Home-page: https://github.com/EbryxLabs/awsip
Author: Rana Awais
Author-email: rana.awais@ebryx.com
License: UNKNOWN
Platform: UNKNOWN
Classifier: Programming Language :: Python :: 3
Classifier: License :: OSI Approved :: MIT License
Classifier: Operating System :: OS Independent
Requires-Dist: requests
